coolledx/__init__.py
coolledx/argparser.py
coolledx/client.py
coolledx/commands.py
coolledx/render.py
coolledx-0.1.0.dist-info/LICENSE
coolledx-0.1.0.dist-info/METADATA
coolledx-0.1.0.dist-info/WHEEL
coolledx-0.1.0.dist-info/RECORD
