Metadata-Version: 2.1
Name: coolledx
Version: 0.1.0
Summary: Driver for the CoolLEDX LED signs (signs managed by CoolLED1248 app)
License: MIT
Author: UpDryTwist
Author-email: tathamg@gmail.com
Requires-Python: >=3.11,<3.13
Classifier: License :: OSI Approved :: MIT License
Classifier: Programming Language :: Python :: 3
Classifier: Programming Language :: Python :: 3.11
Classifier: Programming Language :: Python :: 3.12
Requires-Dist: Pillow (>=10.1.0,<11.0.0)
Requires-Dist: bleak (>=0.21.1,<0.22.0)
